Workbook

Sheet Février 2026
A1: 📊 VSL FUNNEL — FÉVRIER 2026
B2: 📢 DÉPENSES & REACH | G2: 💰 COÛTS UNIT. | I2: 🖥️ LANDING PAGE | L2: 👤 LEADS | O2: 📞 BOOKINGS & APPELS | V2: 💸 COÛT/APPEL | Y2: 🏆 VENTES & CA | AE2: 📈 ROI | AG2: 📝
A3: Date | B3: Dépenses (€) | C3: Impressions | D3: CPM (€) | E3: Clics | F3: CTR (%) | G3: CPC (€) | H3: Coût/Vue LP (€) | I3: Vues LP | J3: Taux Clic→LP (%) | K3: Leads (Formulaire) | L3: CPL (€) | M3: Taux LP→Lead (%) | N3: Leads Qualifiés | O3: Bookings VSL (auto) | P3: Taux Lead→Book (%) | Q3: Leads Non-Bookés | R3: Appels Manuels | S3: Taux Relance (%) | T3: Total Appels | U3: Taux Lead→Appel (%) | V3: Coût/Book VSL (€) | W3: Coût/Appel Manuel (€) | X3: Coût/Appel Total (€) | Y3: Nb Ventes | Z3: Taux Close (%) | AA3: CA Vendu (€) | AB3: Cash Encaissé (€) | AC3: CPA (€) | AD3: P/L (€) | AE3: ROI Vendu (%) | AF3: ROI Cash (%) | AG3: Notes / Actions
A4: 2026-02-01 | D4: =IF(C4=0,"-",B4/C4*1000) -> - | F4: =IF(C4=0,"-",E4/C4) -> - | G4: =IF(E4=0,"-",B4/E4) -> - | H4: =IF(I4=0,"-",B4/I4) -> - | J4: =IF(E4=0,"-",I4/E4) -> - | L4: =IF(K4=0,"-",B4/K4) -> - | M4: =IF(I4=0,"-",K4/I4) -> - | P4: =IF(K4=0,"-",O4/K4) -> - | Q4: =IF(K4="",0,K4-O4) -> 0 | S4: =IF(OR(Q4=0,Q4=""),"-",R4/Q4) -> - | T4: =O4+R4 -> 0 | U4: =IF(K4=0,"-",T4/K4) -> - | V4: =IF(O4=0,"-",B4/O4) -> - | W4: =IF(R4=0,"-",B4/R4) -> - | X4: =IF(T4=0,"-",B4/T4) -> - | Z4: =IF(T4=0,"-",Y4/T4) -> - | AC4: =IF(Y4=0,"-",B4/Y4) -> - | AD4: =AB4-B4 -> 0 | AE4: =IF(B4=0,"-",(AA4-B4)/B4) -> - | AF4: =IF(B4=0,"-",(AB4-B4)/B4) -> -
A5: 2026-02-02 | D5: =IF(C5=0,"-",B5/C5*1000) -> - | F5: =IF(C5=0,"-",E5/C5) -> - | G5: =IF(E5=0,"-",B5/E5) -> - | H5: =IF(I5=0,"-",B5/I5) -> - | J5: =IF(E5=0,"-",I5/E5) -> - | L5: =IF(K5=0,"-",B5/K5) -> - | M5: =IF(I5=0,"-",K5/I5) -> - | P5: =IF(K5=0,"-",O5/K5) -> - | Q5: =IF(K5="",0,K5-O5) -> 0 | S5: =IF(OR(Q5=0,Q5=""),"-",R5/Q5) -> - | T5: =O5+R5 -> 0 | U5: =IF(K5=0,"-",T5/K5) -> - | V5: =IF(O5=0,"-",B5/O5) -> - | W5: =IF(R5=0,"-",B5/R5) -> - | X5: =IF(T5=0,"-",B5/T5) -> - | Z5: =IF(T5=0,"-",Y5/T5) -> - | AC5: =IF(Y5=0,"-",B5/Y5) -> - | AD5: =AB5-B5 -> 0 | AE5: =IF(B5=0,"-",(AA5-B5)/B5) -> - | AF5: =IF(B5=0,"-",(AB5-B5)/B5) -> -
A6: 2026-02-03 | D6: =IF(C6=0,"-",B6/C6*1000) -> - | F6: =IF(C6=0,"-",E6/C6) -> - | G6: =IF(E6=0,"-",B6/E6) -> - | H6: =IF(I6=0,"-",B6/I6) -> - | J6: =IF(E6=0,"-",I6/E6) -> - | L6: =IF(K6=0,"-",B6/K6) -> - | M6: =IF(I6=0,"-",K6/I6) -> - | P6: =IF(K6=0,"-",O6/K6) -> - | Q6: =IF(K6="",0,K6-O6) -> 0 | S6: =IF(OR(Q6=0,Q6=""),"-",R6/Q6) -> - | T6: =O6+R6 -> 0 | U6: =IF(K6=0,"-",T6/K6) -> - | V6: =IF(O6=0,"-",B6/O6) -> - | W6: =IF(R6=0,"-",B6/R6) -> - | X6: =IF(T6=0,"-",B6/T6) -> - | Z6: =IF(T6=0,"-",Y6/T6) -> - | AC6: =IF(Y6=0,"-",B6/Y6) -> - | AD6: =AB6-B6 -> 0 | AE6: =IF(B6=0,"-",(AA6-B6)/B6) -> - | AF6: =IF(B6=0,"-",(AB6-B6)/B6) -> -
A7: 2026-02-04 | D7: =IF(C7=0,"-",B7/C7*1000) -> - | F7: =IF(C7=0,"-",E7/C7) -> - | G7: =IF(E7=0,"-",B7/E7) -> - | H7: =IF(I7=0,"-",B7/I7) -> - | J7: =IF(E7=0,"-",I7/E7) -> - | L7: =IF(K7=0,"-",B7/K7) -> - | M7: =IF(I7=0,"-",K7/I7) -> - | P7: =IF(K7=0,"-",O7/K7) -> - | Q7: =IF(K7="",0,K7-O7) -> 0 | S7: =IF(OR(Q7=0,Q7=""),"-",R7/Q7) -> - | T7: =O7+R7 -> 0 | U7: =IF(K7=0,"-",T7/K7) -> - | V7: =IF(O7=0,"-",B7/O7) -> - | W7: =IF(R7=0,"-",B7/R7) -> - | X7: =IF(T7=0,"-",B7/T7) -> - | Z7: =IF(T7=0,"-",Y7/T7) -> - | AC7: =IF(Y7=0,"-",B7/Y7) -> - | AD7: =AB7-B7 -> 0 | AE7: =IF(B7=0,"-",(AA7-B7)/B7) -> - | AF7: =IF(B7=0,"-",(AB7-B7)/B7) -> -
A8: 2026-02-05 | D8: =IF(C8=0,"-",B8/C8*1000) -> - | F8: =IF(C8=0,"-",E8/C8) -> - | G8: =IF(E8=0,"-",B8/E8) -> - | H8: =IF(I8=0,"-",B8/I8) -> - | J8: =IF(E8=0,"-",I8/E8) -> - | L8: =IF(K8=0,"-",B8/K8) -> - | M8: =IF(I8=0,"-",K8/I8) -> - | P8: =IF(K8=0,"-",O8/K8) -> - | Q8: =IF(K8="",0,K8-O8) -> 0 | S8: =IF(OR(Q8=0,Q8=""),"-",R8/Q8) -> - | T8: =O8+R8 -> 0 | U8: =IF(K8=0,"-",T8/K8) -> - | V8: =IF(O8=0,"-",B8/O8) -> - | W8: =IF(R8=0,"-",B8/R8) -> - | X8: =IF(T8=0,"-",B8/T8) -> - | Z8: =IF(T8=0,"-",Y8/T8) -> - | AC8: =IF(Y8=0,"-",B8/Y8) -> - | AD8: =AB8-B8 -> 0 | AE8: =IF(B8=0,"-",(AA8-B8)/B8) -> - | AF8: =IF(B8=0,"-",(AB8-B8)/B8) -> -
A9: 2026-02-06 | D9: =IF(C9=0,"-",B9/C9*1000) -> - | F9: =IF(C9=0,"-",E9/C9) -> - | G9: =IF(E9=0,"-",B9/E9) -> - | H9: =IF(I9=0,"-",B9/I9) -> - | J9: =IF(E9=0,"-",I9/E9) -> - | L9: =IF(K9=0,"-",B9/K9) -> - | M9: =IF(I9=0,"-",K9/I9) -> - | P9: =IF(K9=0,"-",O9/K9) -> - | Q9: =IF(K9="",0,K9-O9) -> 0 | S9: =IF(OR(Q9=0,Q9=""),"-",R9/Q9) -> - | T9: =O9+R9 -> 0 | U9: =IF(K9=0,"-",T9/K9) -> - | V9: =IF(O9=0,"-",B9/O9) -> - | W9: =IF(R9=0,"-",B9/R9) -> - | X9: =IF(T9=0,"-",B9/T9) -> - | Z9: =IF(T9=0,"-",Y9/T9) -> - | AC9: =IF(Y9=0,"-",B9/Y9) -> - | AD9: =AB9-B9 -> 0 | AE9: =IF(B9=0,"-",(AA9-B9)/B9) -> - | AF9: =IF(B9=0,"-",(AB9-B9)/B9) -> -
A10: 2026-02-07 | D10: =IF(C10=0,"-",B10/C10*1000) -> - | F10: =IF(C10=0,"-",E10/C10) -> - | G10: =IF(E10=0,"-",B10/E10) -> - | H10: =IF(I10=0,"-",B10/I10) -> - | J10: =IF(E10=0,"-",I10/E10) -> - | L10: =IF(K10=0,"-",B10/K10) -> - | M10: =IF(I10=0,"-",K10/I10) -> - | P10: =IF(K10=0,"-",O10/K10) -> - | Q10: =IF(K10="",0,K10-O10) -> 0 | S10: =IF(OR(Q10=0,Q10=""),"-",R10/Q10) -> - | T10: =O10+R10 -> 0 | U10: =IF(K10=0,"-",T10/K10) -> - | V10: =IF(O10=0,"-",B10/O10) -> - | W10: =IF(R10=0,"-",B10/R10) -> - | X10: =IF(T10=0,"-",B10/T10) -> - | Z10: =IF(T10=0,"-",Y10/T10) -> - | AC10: =IF(Y10=0,"-",B10/Y10) -> - | AD10: =AB10-B10 -> 0 | AE10: =IF(B10=0,"-",(AA10-B10)/B10) -> - | AF10: =IF(B10=0,"-",(AB10-B10)/B10) -> -
A11: 2026-02-08 | D11: =IF(C11=0,"-",B11/C11*1000) -> - | F11: =IF(C11=0,"-",E11/C11) -> - | G11: =IF(E11=0,"-",B11/E11) -> - | H11: =IF(I11=0,"-",B11/I11) -> - | J11: =IF(E11=0,"-",I11/E11) -> - | L11: =IF(K11=0,"-",B11/K11) -> - | M11: =IF(I11=0,"-",K11/I11) -> - | P11: =IF(K11=0,"-",O11/K11) -> - | Q11: =IF(K11="",0,K11-O11) -> 0 | S11: =IF(OR(Q11=0,Q11=""),"-",R11/Q11) -> - | T11: =O11+R11 -> 0 | U11: =IF(K11=0,"-",T11/K11) -> - | V11: =IF(O11=0,"-",B11/O11) -> - | W11: =IF(R11=0,"-",B11/R11) -> - | X11: =IF(T11=0,"-",B11/T11) -> - | Z11: =IF(T11=0,"-",Y11/T11) -> - | AC11: =IF(Y11=0,"-",B11/Y11) -> - | AD11: =AB11-B11 -> 0 | AE11: =IF(B11=0,"-",(AA11-B11)/B11) -> - | AF11: =IF(B11=0,"-",(AB11-B11)/B11) -> -
A12: 2026-02-09 | D12: =IF(C12=0,"-",B12/C12*1000) -> - | F12: =IF(C12=0,"-",E12/C12) -> - | G12: =IF(E12=0,"-",B12/E12) -> - | H12: =IF(I12=0,"-",B12/I12) -> - | J12: =IF(E12=0,"-",I12/E12) -> - | L12: =IF(K12=0,"-",B12/K12) -> - | M12: =IF(I12=0,"-",K12/I12) -> - | P12: =IF(K12=0,"-",O12/K12) -> - | Q12: =IF(K12="",0,K12-O12) -> 0 | S12: =IF(OR(Q12=0,Q12=""),"-",R12/Q12) -> - | T12: =O12+R12 -> 0 | U12: =IF(K12=0,"-",T12/K12) -> - | V12: =IF(O12=0,"-",B12/O12) -> - | W12: =IF(R12=0,"-",B12/R12) -> - | X12: =IF(T12=0,"-",B12/T12) -> - | Z12: =IF(T12=0,"-",Y12/T12) -> - | AC12: =IF(Y12=0,"-",B12/Y12) -> - | AD12: =AB12-B12 -> 0 | AE12: =IF(B12=0,"-",(AA12-B12)/B12) -> - | AF12: =IF(B12=0,"-",(AB12-B12)/B12) -> -
A13: 2026-02-10 | D13: =IF(C13=0,"-",B13/C13*1000) -> - | F13: =IF(C13=0,"-",E13/C13) -> - | G13: =IF(E13=0,"-",B13/E13) -> - | H13: =IF(I13=0,"-",B13/I13) -> - | J13: =IF(E13=0,"-",I13/E13) -> - | L13: =IF(K13=0,"-",B13/K13) -> - | M13: =IF(I13=0,"-",K13/I13) -> - | P13: =IF(K13=0,"-",O13/K13) -> - | Q13: =IF(K13="",0,K13-O13) -> 0 | S13: =IF(OR(Q13=0,Q13=""),"-",R13/Q13) -> - | T13: =O13+R13 -> 0 | U13: =IF(K13=0,"-",T13/K13) -> - | V13: =IF(O13=0,"-",B13/O13) -> - | W13: =IF(R13=0,"-",B13/R13) -> - | X13: =IF(T13=0,"-",B13/T13) -> - | Z13: =IF(T13=0,"-",Y13/T13) -> - | AC13: =IF(Y13=0,"-",B13/Y13) -> - | AD13: =AB13-B13 -> 0 | AE13: =IF(B13=0,"-",(AA13-B13)/B13) -> - | AF13: =IF(B13=0,"-",(AB13-B13)/B13) -> -
A14: 2026-02-11 | D14: =IF(C14=0,"-",B14/C14*1000) -> - | F14: =IF(C14=0,"-",E14/C14) -> - | G14: =IF(E14=0,"-",B14/E14) -> - | H14: =IF(I14=0,"-",B14/I14) -> - | J14: =IF(E14=0,"-",I14/E14) -> - | L14: =IF(K14=0,"-",B14/K14) -> - | M14: =IF(I14=0,"-",K14/I14) -> - | P14: =IF(K14=0,"-",O14/K14) -> - | Q14: =IF(K14="",0,K14-O14) -> 0 | S14: =IF(OR(Q14=0,Q14=""),"-",R14/Q14) -> - | T14: =O14+R14 -> 0 | U14: =IF(K14=0,"-",T14/K14) -> - | V14: =IF(O14=0,"-",B14/O14) -> - | W14: =IF(R14=0,"-",B14/R14) -> - | X14: =IF(T14=0,"-",B14/T14) -> - | Z14: =IF(T14=0,"-",Y14/T14) -> - | AC14: =IF(Y14=0,"-",B14/Y14) -> - | AD14: =AB14-B14 -> 0 | AE14: =IF(B14=0,"-",(AA14-B14)/B14) -> - | AF14: =IF(B14=0,"-",(AB14-B14)/B14) -> -
A15: 2026-02-12 | D15: =IF(C15=0,"-",B15/C15*1000) -> - | F15: =IF(C15=0,"-",E15/C15) -> - | G15: =IF(E15=0,"-",B15/E15) -> - | H15: =IF(I15=0,"-",B15/I15) -> - | J15: =IF(E15=0,"-",I15/E15) -> - | L15: =IF(K15=0,"-",B15/K15) -> - | M15: =IF(I15=0,"-",K15/I15) -> - | P15: =IF(K15=0,"-",O15/K15) -> - | Q15: =IF(K15="",0,K15-O15) -> 0 | S15: =IF(OR(Q15=0,Q15=""),"-",R15/Q15) -> - | T15: =O15+R15 -> 0 | U15: =IF(K15=0,"-",T15/K15) -> - | V15: =IF(O15=0,"-",B15/O15) -> - | W15: =IF(R15=0,"-",B15/R15) -> - | X15: =IF(T15=0,"-",B15/T15) -> - | Z15: =IF(T15=0,"-",Y15/T15) -> - | AC15: =IF(Y15=0,"-",B15/Y15) -> - | AD15: =AB15-B15 -> 0 | AE15: =IF(B15=0,"-",(AA15-B15)/B15) -> - | AF15: =IF(B15=0,"-",(AB15-B15)/B15) -> -
... A31: 2026-02-28 | D31: =IF(C31=0,"-",B31/C31*1000) -> - | F31: =IF(C31=0,"-",E31/C31) -> - | G31: =IF(E31=0,"-",B31/E31) -> - | H31: =IF(I31=0,"-",B31/I31) -> - | J31: =IF(E31=0,"-",I31/E31) -> - | L31: =IF(K31=0,"-",B31/K31) -> - | M31: =IF(I31=0,"-",K31/I31) -> - | P31: =IF(K31=0,"-",O31/K31) -> - | Q31: =IF(K31="",0,K31-O31) -> 0 | S31: =IF(OR(Q31=0,Q31=""),"-",R31/Q31) -> - | T31: =O31+R31 -> 0 | U31: =IF(K31=0,"-",T31/K31) -> - | V31: =IF(O31=0,"-",B31/O31) -> - | W31: =IF(R31=0,"-",B31/R31) -> - | X31: =IF(T31=0,"-",B31/T31) -> - | Z31: =IF(T31=0,"-",Y31/T31) -> - | AC31: =IF(Y31=0,"-",B31/Y31) -> - | AD31: =AB31-B31 -> 0 | AE31: =IF(B31=0,"-",(AA31-B31)/B31) -> - | AF31: =IF(B31=0,"-",(AB31-B31)/B31) -> -
A32: TOTAL / MOY. | B32: =SUM(B4:B31) -> 0 | C32: =SUM(C4:C31) -> 0 | D32: =IF(C32=0,"-",B32/C32*1000) -> - | E32: =SUM(E4:E31) -> 0 | F32: =IF(C32=0,"-",E32/C32) -> - | G32: =IF(E32=0,"-",B32/E32) -> - | H32: =IF(I32=0,"-",B32/I32) -> - | I32: =SUM(I4:I31) -> 0 | J32: =IF(E32=0,"-",I32/E32) -> - | K32: =SUM(K4:K31) -> 0 | L32: =IF(K32=0,"-",B32/K32) -> - | M32: =IF(I32=0,"-",K32/I32) -> - | N32: =SUM(N4:N31) -> 0 | O32: =SUM(O4:O31) -> 0 | P32: =IF(K32=0,"-",O32/K32) -> - | Q32: =K32-O32 -> 0 | R32: =SUM(R4:R31) -> 0 | S32: =IF(Q32=0,"-",R32/Q32) -> - | T32: =SUM(T4:T31) -> 0 | U32: =IF(K32=0,"-",T32/K32) -> - | V32: =IF(O32=0,"-",B32/O32) -> - | W32: =IF(R32=0,"-",B32/R32) -> - | X32: =IF(T32=0,"-",B32/T32) -> - | Y32: =SUM(Y4:Y31) -> 0 | Z32: =IF(T32=0,"-",Y32/T32) -> - | AA32: =SUM(AA4:AA31) -> 0 | AB32: =SUM(AB4:AB31) -> 0 | AC32: =IF(Y32=0,"-",B32/Y32) -> - | AD32: =AB32-B32 -> 0 | AE32: =IF(B32=0,"-",(AA32-B32)/B32) -> - | AF32: =IF(B32=0,"-",(AB32-B32)/B32) -> -

Sheet Suivi par Ad
A1: 📢 SUIVI PAR AD — PERFORMANCE INDIVIDUELLE
A2: Nom de l'Ad | B2: Créa / Angle | C2: Date Lancement | D2: Statut | E2: Dépenses (€) | F2: Impressions | G2: CPM (€) | H2: Clics | I2: CTR (%) | J2: CPC (€) | K2: Vues LP | L2: Coût/Vue LP (€) | M2: Leads | N2: CPL (€) | O2: Bookings VSL | P2: Appels Manuels | Q2: Total Appels | R2: Coût/Appel (€) | S2: Ventes | T2: CPA (€) | U2: CA (€) | V2: ROI (%) | W2: Score (/10) | X2: Notes
G3: =IF(F3=0,"-",E3/F3*1000) -> - | I3: =IF(F3=0,"-",H3/F3) -> - | J3: =IF(H3=0,"-",E3/H3) -> - | L3: =IF(K3=0,"-",E3/K3) -> - | N3: =IF(M3=0,"-",E3/M3) -> - | Q3: =O3+P3 -> 0 | R3: =IF(Q3=0,"-",E3/Q3) -> - | T3: =IF(S3=0,"-",E3/S3) -> - | V3: =IF(E3=0,"-",(U3-E3)/E3) -> -
G4: =IF(F4=0,"-",E4/F4*1000) -> - | I4: =IF(F4=0,"-",H4/F4) -> - | J4: =IF(H4=0,"-",E4/H4) -> - | L4: =IF(K4=0,"-",E4/K4) -> - | N4: =IF(M4=0,"-",E4/M4) -> - | Q4: =O4+P4 -> 0 | R4: =IF(Q4=0,"-",E4/Q4) -> - | T4: =IF(S4=0,"-",E4/S4) -> - | V4: =IF(E4=0,"-",(U4-E4)/E4) -> -
G5: =IF(F5=0,"-",E5/F5*1000) -> - | I5: =IF(F5=0,"-",H5/F5) -> - | J5: =IF(H5=0,"-",E5/H5) -> - | L5: =IF(K5=0,"-",E5/K5) -> - | N5: =IF(M5=0,"-",E5/M5) -> - | Q5: =O5+P5 -> 0 | R5: =IF(Q5=0,"-",E5/Q5) -> - | T5: =IF(S5=0,"-",E5/S5) -> - | V5: =IF(E5=0,"-",(U5-E5)/E5) -> -
G6: =IF(F6=0,"-",E6/F6*1000) -> - | I6: =IF(F6=0,"-",H6/F6) -> - | J6: =IF(H6=0,"-",E6/H6) -> - | L6: =IF(K6=0,"-",E6/K6) -> - | N6: =IF(M6=0,"-",E6/M6) -> - | Q6: =O6+P6 -> 0 | R6: =IF(Q6=0,"-",E6/Q6) -> - | T6: =IF(S6=0,"-",E6/S6) -> - | V6: =IF(E6=0,"-",(U6-E6)/E6) -> -
G7: =IF(F7=0,"-",E7/F7*1000) -> - | I7: =IF(F7=0,"-",H7/F7) -> - | J7: =IF(H7=0,"-",E7/H7) -> - | L7: =IF(K7=0,"-",E7/K7) -> - | N7: =IF(M7=0,"-",E7/M7) -> - | Q7: =O7+P7 -> 0 | R7: =IF(Q7=0,"-",E7/Q7) -> - | T7: =IF(S7=0,"-",E7/S7) -> - | V7: =IF(E7=0,"-",(U7-E7)/E7) -> -
G8: =IF(F8=0,"-",E8/F8*1000) -> - | I8: =IF(F8=0,"-",H8/F8) -> - | J8: =IF(H8=0,"-",E8/H8) -> - | L8: =IF(K8=0,"-",E8/K8) -> - | N8: =IF(M8=0,"-",E8/M8) -> - | Q8: =O8+P8 -> 0 | R8: =IF(Q8=0,"-",E8/Q8) -> - | T8: =IF(S8=0,"-",E8/S8) -> - | V8: =IF(E8=0,"-",(U8-E8)/E8) -> -
G9: =IF(F9=0,"-",E9/F9*1000) -> - | I9: =IF(F9=0,"-",H9/F9) -> - | J9: =IF(H9=0,"-",E9/H9) -> - | L9: =IF(K9=0,"-",E9/K9) -> - | N9: =IF(M9=0,"-",E9/M9) -> - | Q9: =O9+P9 -> 0 | R9: =IF(Q9=0,"-",E9/Q9) -> - | T9: =IF(S9=0,"-",E9/S9) -> - | V9: =IF(E9=0,"-",(U9-E9)/E9) -> -
G10: =IF(F10=0,"-",E10/F10*1000) -> - | I10: =IF(F10=0,"-",H10/F10) -> - | J10: =IF(H10=0,"-",E10/H10) -> - | L10: =IF(K10=0,"-",E10/K10) -> - | N10: =IF(M10=0,"-",E10/M10) -> - | Q10: =O10+P10 -> 0 | R10: =IF(Q10=0,"-",E10/Q10) -> - | T10: =IF(S10=0,"-",E10/S10) -> - | V10: =IF(E10=0,"-",(U10-E10)/E10) -> -
G11: =IF(F11=0,"-",E11/F11*1000) -> - | I11: =IF(F11=0,"-",H11/F11) -> - | J11: =IF(H11=0,"-",E11/H11) -> - | L11: =IF(K11=0,"-",E11/K11) -> - | N11: =IF(M11=0,"-",E11/M11) -> - | Q11: =O11+P11 -> 0 | R11: =IF(Q11=0,"-",E11/Q11) -> - | T11: =IF(S11=0,"-",E11/S11) -> - | V11: =IF(E11=0,"-",(U11-E11)/E11) -> -
G12: =IF(F12=0,"-",E12/F12*1000) -> - | I12: =IF(F12=0,"-",H12/F12) -> - | J12: =IF(H12=0,"-",E12/H12) -> - | L12: =IF(K12=0,"-",E12/K12) -> - | N12: =IF(M12=0,"-",E12/M12) -> - | Q12: =O12+P12 -> 0 | R12: =IF(Q12=0,"-",E12/Q12) -> - | T12: =IF(S12=0,"-",E12/S12) -> - | V12: =IF(E12=0,"-",(U12-E12)/E12) -> -
G13: =IF(F13=0,"-",E13/F13*1000) -> - | I13: =IF(F13=0,"-",H13/F13) -> - | J13: =IF(H13=0,"-",E13/H13) -> - | L13: =IF(K13=0,"-",E13/K13) -> - | N13: =IF(M13=0,"-",E13/M13) -> - | Q13: =O13+P13 -> 0 | R13: =IF(Q13=0,"-",E13/Q13) -> - | T13: =IF(S13=0,"-",E13/S13) -> - | V13: =IF(E13=0,"-",(U13-E13)/E13) -> -
G14: =IF(F14=0,"-",E14/F14*1000) -> - | I14: =IF(F14=0,"-",H14/F14) -> - | J14: =IF(H14=0,"-",E14/H14) -> - | L14: =IF(K14=0,"-",E14/K14) -> - | N14: =IF(M14=0,"-",E14/M14) -> - | Q14: =O14+P14 -> 0 | R14: =IF(Q14=0,"-",E14/Q14) -> - | T14: =IF(S14=0,"-",E14/S14) -> - | V14: =IF(E14=0,"-",(U14-E14)/E14) -> -
... G22: =IF(F22=0,"-",E22/F22*1000) -> - | I22: =IF(F22=0,"-",H22/F22) -> - | J22: =IF(H22=0,"-",E22/H22) -> - | L22: =IF(K22=0,"-",E22/K22) -> - | N22: =IF(M22=0,"-",E22/M22) -> - | Q22: =O22+P22 -> 0 | R22: =IF(Q22=0,"-",E22/Q22) -> - | T22: =IF(S22=0,"-",E22/S22) -> - | V22: =IF(E22=0,"-",(U22-E22)/E22) -> -

Sheet KPIs & Diagnostic
A1: 🎯 KPIs & DIAGNOSTIC FUNNEL VSL
A3: 🔍 ÉTAPE DU FUNNEL | B3: Volume | C3: Taux Conv. | D3: Coût Unitaire (€) | E3: Benchmark | F3: Statut | G3: Action Prioritaire
A4: Impressions | B4: ='Février 2026'!C32 -> 0 | E4: >10k/sem
A5: Clics | B5: ='Février 2026'!E32 -> 0 | C5: ='Février 2026'!F32 -> - | D5: ='Février 2026'!G32 -> - | E5: CTR >1%
A6: Vues Landing Page | B6: ='Février 2026'!I32 -> 0 | C6: ='Février 2026'!J32 -> - | D6: ='Février 2026'!H32 -> - | E6: >80% clics
A7: Leads (Formulaire) | B7: ='Février 2026'!K32 -> 0 | C7: ='Février 2026'!M32 -> - | D7: ='Février 2026'!L32 -> - | E7: Opt-in >20%
A8: Bookings VSL (auto) | B8: ='Février 2026'!O32 -> 0 | C8: ='Février 2026'!P32 -> - | D8: ='Février 2026'!V32 -> - | E8: >30% leads
A9: Appels Manuels | B9: ='Février 2026'!R32 -> 0 | C9: ='Février 2026'!S32 -> - | D9: ='Février 2026'!W32 -> -
A10: Total Appels | B10: ='Février 2026'!T32 -> 0 | C10: ='Février 2026'!U32 -> - | D10: ='Février 2026'!X32 -> - | E10: >50% leads
A11: Ventes | B11: ='Février 2026'!Y32 -> 0 | C11: ='Février 2026'!Z32 -> - | D11: ='Février 2026'!AC32 -> - | E11: Close >20%
A13: ⚠️ DIAGNOSTIC : GAP LEADS → BOOKINGS (Ton problème principal)
A14: Métrique | B14: Valeur | C14: Objectif | D14: Écart | E14: Impact
A15: Total Leads | B15: ='Février 2026'!K32 -> 0
A16: Bookings Auto (VSL) | B16: ='Février 2026'!O32 -> 0
A17: Leads Non-Bookés | B17: ='Février 2026'!Q32 -> 0 | E17: Leads perdus sans relance
A18: Relances Manuelles | B18: ='Février 2026'!R32 -> 0
A19: Taux Booking Auto | B19: ='Février 2026'!P32 -> - | C19: >30% | E19: Si <15% → VSL ou CTA à revoir
A20: Taux Relance Réussie | B20: ='Février 2026'!S32 -> - | C20: >60% | E20: Efficacité de tes appels
A21: Taux Total Lead→Appel | B21: ='Février 2026'!U32 -> - | C21: >50% | E21: KPI clé à maximiser
A24: 💶 RÉSUMÉ FINANCIER DU MOIS
A25: Total Dépensé | B25: ='Février 2026'!B32 -> 0
A26: CA Vendu | B26: ='Février 2026'!AA32 -> 0
A27: Cash Encaissé | B27: ='Février 2026'!AB32 -> 0
A28: P/L | B28: ='Février 2026'!AD32 -> 0
A29: ROI sur Ventes | B29: ='Février 2026'!AE32 -> -
A30: ROI sur Cash | B30: ='Février 2026'!AF32 -> -
A31: CPA Moyen | B31: ='Février 2026'!AC32 -> -

Sheet Suivi Hebdomadaire
A1: 📅 SUIVI HEBDOMADAIRE — TENDANCES
A2: Semaine | B2: Dates | C2: Dépenses (€) | D2: Impressions | E2: CPM (€) | F2: Clics | G2: CTR (%) | H2: CPC (€) | I2: Vues LP | J2: Leads | K2: CPL (€) | L2: Bookings VSL | M2: Taux Book (%) | N2: Appels Manuels | O2: Total Appels | P2: Coût/Appel (€) | Q2: Ventes | R2: Taux Close (%) | S2: CA (€) | T2: Cash (€) | U2: CPA (€) | V2: ROI (%) | W2: Notes Semaine
A3: S1 | E3: =IF(D3=0,"-",C3/D3*1000) -> - | G3: =IF(D3=0,"-",F3/D3) -> - | H3: =IF(F3=0,"-",C3/F3) -> - | K3: =IF(J3=0,"-",C3/J3) -> - | M3: =IF(J3=0,"-",L3/J3) -> - | O3: =L3+N3 -> 0 | P3: =IF(O3=0,"-",C3/O3) -> - | R3: =IF(O3=0,"-",Q3/O3) -> - | U3: =IF(Q3=0,"-",C3/Q3) -> - | V3: =IF(C3=0,"-",(T3-C3)/C3) -> -
A4: S2 | E4: =IF(D4=0,"-",C4/D4*1000) -> - | G4: =IF(D4=0,"-",F4/D4) -> - | H4: =IF(F4=0,"-",C4/F4) -> - | K4: =IF(J4=0,"-",C4/J4) -> - | M4: =IF(J4=0,"-",L4/J4) -> - | O4: =L4+N4 -> 0 | P4: =IF(O4=0,"-",C4/O4) -> - | R4: =IF(O4=0,"-",Q4/O4) -> - | U4: =IF(Q4=0,"-",C4/Q4) -> - | V4: =IF(C4=0,"-",(T4-C4)/C4) -> -
A5: S3 | E5: =IF(D5=0,"-",C5/D5*1000) -> - | G5: =IF(D5=0,"-",F5/D5) -> - | H5: =IF(F5=0,"-",C5/F5) -> - | K5: =IF(J5=0,"-",C5/J5) -> - | M5: =IF(J5=0,"-",L5/J5) -> - | O5: =L5+N5 -> 0 | P5: =IF(O5=0,"-",C5/O5) -> - | R5: =IF(O5=0,"-",Q5/O5) -> - | U5: =IF(Q5=0,"-",C5/Q5) -> - | V5: =IF(C5=0,"-",(T5-C5)/C5) -> -
A6: S4 | E6: =IF(D6=0,"-",C6/D6*1000) -> - | G6: =IF(D6=0,"-",F6/D6) -> - | H6: =IF(F6=0,"-",C6/F6) -> - | K6: =IF(J6=0,"-",C6/J6) -> - | M6: =IF(J6=0,"-",L6/J6) -> - | O6: =L6+N6 -> 0 | P6: =IF(O6=0,"-",C6/O6) -> - | R6: =IF(O6=0,"-",Q6/O6) -> - | U6: =IF(Q6=0,"-",C6/Q6) -> - | V6: =IF(C6=0,"-",(T6-C6)/C6) -> -
A7: S5 | E7: =IF(D7=0,"-",C7/D7*1000) -> - | G7: =IF(D7=0,"-",F7/D7) -> - | H7: =IF(F7=0,"-",C7/F7) -> - | K7: =IF(J7=0,"-",C7/J7) -> - | M7: =IF(J7=0,"-",L7/J7) -> - | O7: =L7+N7 -> 0 | P7: =IF(O7=0,"-",C7/O7) -> - | R7: =IF(O7=0,"-",Q7/O7) -> - | U7: =IF(Q7=0,"-",C7/Q7) -> - | V7: =IF(C7=0,"-",(T7-C7)/C7) -> -
A8: S6 | E8: =IF(D8=0,"-",C8/D8*1000) -> - | G8: =IF(D8=0,"-",F8/D8) -> - | H8: =IF(F8=0,"-",C8/F8) -> - | K8: =IF(J8=0,"-",C8/J8) -> - | M8: =IF(J8=0,"-",L8/J8) -> - | O8: =L8+N8 -> 0 | P8: =IF(O8=0,"-",C8/O8) -> - | R8: =IF(O8=0,"-",Q8/O8) -> - | U8: =IF(Q8=0,"-",C8/Q8) -> - | V8: =IF(C8=0,"-",(T8-C8)/C8) -> -
A9: S7 | E9: =IF(D9=0,"-",C9/D9*1000) -> - | G9: =IF(D9=0,"-",F9/D9) -> - | H9: =IF(F9=0,"-",C9/F9) -> - | K9: =IF(J9=0,"-",C9/J9) -> - | M9: =IF(J9=0,"-",L9/J9) -> - | O9: =L9+N9 -> 0 | P9: =IF(O9=0,"-",C9/O9) -> - | R9: =IF(O9=0,"-",Q9/O9) -> - | U9: =IF(Q9=0,"-",C9/Q9) -> - | V9: =IF(C9=0,"-",(T9-C9)/C9) -> -
A10: S8 | E10: =IF(D10=0,"-",C10/D10*1000) -> - | G10: =IF(D10=0,"-",F10/D10) -> - | H10: =IF(F10=0,"-",C10/F10) -> - | K10: =IF(J10=0,"-",C10/J10) -> - | M10: =IF(J10=0,"-",L10/J10) -> - | O10: =L10+N10 -> 0 | P10: =IF(O10=0,"-",C10/O10) -> - | R10: =IF(O10=0,"-",Q10/O10) -> - | U10: =IF(Q10=0,"-",C10/Q10) -> - | V10: =IF(C10=0,"-",(T10-C10)/C10) -> -

Sheet Dashboard Visuel
A1: 📊 DASHBOARD VISUEL — VSL FUNNEL SCALINGFLOW
A2: Jour | B2: Dépenses | C2: CPM | D2: CPC | E2: CTR | F2: Vues LP | G2: Leads | H2: CPL | I2: Bookings VSL | J2: Appels Manuels | K2: Total Appels | L2: Coût/Book VSL | M2: Coût/Appel Manuel | N2: Coût/Appel Total | O2: Ventes | P2: Taux Close | Q2: CA | R2: P/L | S2: ROI Cash
A3: 1 | B3: ='Février 2026'!B4 | C3: ='Février 2026'!D4 -> - | D3: ='Février 2026'!G4 -> - | E3: ='Février 2026'!F4 -> - | F3: ='Février 2026'!I4 | G3: ='Février 2026'!K4 | H3: ='Février 2026'!L4 -> - | I3: ='Février 2026'!O4 | J3: ='Février 2026'!R4 | K3: ='Février 2026'!T4 -> 0 | L3: ='Février 2026'!V4 -> - | M3: ='Février 2026'!W4 -> - | N3: ='Février 2026'!X4 -> - | O3: ='Février 2026'!Y4 | P3: ='Février 2026'!Z4 -> - | Q3: ='Février 2026'!AA4 | R3: ='Février 2026'!AD4 -> 0 | S3: ='Février 2026'!AF4 -> -
A4: 2 | B4: ='Février 2026'!B5 | C4: ='Février 2026'!D5 -> - | D4: ='Février 2026'!G5 -> - | E4: ='Février 2026'!F5 -> - | F4: ='Février 2026'!I5 | G4: ='Février 2026'!K5 | H4: ='Février 2026'!L5 -> - | I4: ='Février 2026'!O5 | J4: ='Février 2026'!R5 | K4: ='Février 2026'!T5 -> 0 | L4: ='Février 2026'!V5 -> - | M4: ='Février 2026'!W5 -> - | N4: ='Février 2026'!X5 -> - | O4: ='Février 2026'!Y5 | P4: ='Février 2026'!Z5 -> - | Q4: ='Février 2026'!AA5 | R4: ='Février 2026'!AD5 -> 0 | S4: ='Février 2026'!AF5 -> -
A5: 3 | B5: ='Février 2026'!B6 | C5: ='Février 2026'!D6 -> - | D5: ='Février 2026'!G6 -> - | E5: ='Février 2026'!F6 -> - | F5: ='Février 2026'!I6 | G5: ='Février 2026'!K6 | H5: ='Février 2026'!L6 -> - | I5: ='Février 2026'!O6 | J5: ='Février 2026'!R6 | K5: ='Février 2026'!T6 -> 0 | L5: ='Février 2026'!V6 -> - | M5: ='Février 2026'!W6 -> - | N5: ='Février 2026'!X6 -> - | O5: ='Février 2026'!Y6 | P5: ='Février 2026'!Z6 -> - | Q5: ='Février 2026'!AA6 | R5: ='Février 2026'!AD6 -> 0 | S5: ='Février 2026'!AF6 -> -
A6: 4 | B6: ='Février 2026'!B7 | C6: ='Février 2026'!D7 -> - | D6: ='Février 2026'!G7 -> - | E6: ='Février 2026'!F7 -> - | F6: ='Février 2026'!I7 | G6: ='Février 2026'!K7 | H6: ='Février 2026'!L7 -> - | I6: ='Février 2026'!O7 | J6: ='Février 2026'!R7 | K6: ='Février 2026'!T7 -> 0 | L6: ='Février 2026'!V7 -> - | M6: ='Février 2026'!W7 -> - | N6: ='Février 2026'!X7 -> - | O6: ='Février 2026'!Y7 | P6: ='Février 2026'!Z7 -> - | Q6: ='Février 2026'!AA7 | R6: ='Février 2026'!AD7 -> 0 | S6: ='Février 2026'!AF7 -> -
A7: 5 | B7: ='Février 2026'!B8 | C7: ='Février 2026'!D8 -> - | D7: ='Février 2026'!G8 -> - | E7: ='Février 2026'!F8 -> - | F7: ='Février 2026'!I8 | G7: ='Février 2026'!K8 | H7: ='Février 2026'!L8 -> - | I7: ='Février 2026'!O8 | J7: ='Février 2026'!R8 | K7: ='Février 2026'!T8 -> 0 | L7: ='Février 2026'!V8 -> - | M7: ='Février 2026'!W8 -> - | N7: ='Février 2026'!X8 -> - | O7: ='Février 2026'!Y8 | P7: ='Février 2026'!Z8 -> - | Q7: ='Février 2026'!AA8 | R7: ='Février 2026'!AD8 -> 0 | S7: ='Février 2026'!AF8 -> -
A8: 6 | B8: ='Février 2026'!B9 | C8: ='Février 2026'!D9 -> - | D8: ='Février 2026'!G9 -> - | E8: ='Février 2026'!F9 -> - | F8: ='Février 2026'!I9 | G8: ='Février 2026'!K9 | H8: ='Février 2026'!L9 -> - | I8: ='Février 2026'!O9 | J8: ='Février 2026'!R9 | K8: ='Février 2026'!T9 -> 0 | L8: ='Février 2026'!V9 -> - | M8: ='Février 2026'!W9 -> - | N8: ='Février 2026'!X9 -> - | O8: ='Février 2026'!Y9 | P8: ='Février 2026'!Z9 -> - | Q8: ='Février 2026'!AA9 | R8: ='Février 2026'!AD9 -> 0 | S8: ='Février 2026'!AF9 -> -
A9: 7 | B9: ='Février 2026'!B10 | C9: ='Février 2026'!D10 -> - | D9: ='Février 2026'!G10 -> - | E9: ='Février 2026'!F10 -> - | F9: ='Février 2026'!I10 | G9: ='Février 2026'!K10 | H9: ='Février 2026'!L10 -> - | I9: ='Février 2026'!O10 | J9: ='Février 2026'!R10 | K9: ='Février 2026'!T10 -> 0 | L9: ='Février 2026'!V10 -> - | M9: ='Février 2026'!W10 -> - | N9: ='Février 2026'!X10 -> - | O9: ='Février 2026'!Y10 | P9: ='Février 2026'!Z10 -> - | Q9: ='Février 2026'!AA10 | R9: ='Février 2026'!AD10 -> 0 | S9: ='Février 2026'!AF10 -> -
A10: 8 | B10: ='Février 2026'!B11 | C10: ='Février 2026'!D11 -> - | D10: ='Février 2026'!G11 -> - | E10: ='Février 2026'!F11 -> - | F10: ='Février 2026'!I11 | G10: ='Février 2026'!K11 | H10: ='Février 2026'!L11 -> - | I10: ='Février 2026'!O11 | J10: ='Février 2026'!R11 | K10: ='Février 2026'!T11 -> 0 | L10: ='Février 2026'!V11 -> - | M10: ='Février 2026'!W11 -> - | N10: ='Février 2026'!X11 -> - | O10: ='Février 2026'!Y11 | P10: ='Février 2026'!Z11 -> - | Q10: ='Février 2026'!AA11 | R10: ='Février 2026'!AD11 -> 0 | S10: ='Février 2026'!AF11 -> -
A11: 9 | B11: ='Février 2026'!B12 | C11: ='Février 2026'!D12 -> - | D11: ='Février 2026'!G12 -> - | E11: ='Février 2026'!F12 -> - | F11: ='Février 2026'!I12 | G11: ='Février 2026'!K12 | H11: ='Février 2026'!L12 -> - | I11: ='Février 2026'!O12 | J11: ='Février 2026'!R12 | K11: ='Février 2026'!T12 -> 0 | L11: ='Février 2026'!V12 -> - | M11: ='Février 2026'!W12 -> - | N11: ='Février 2026'!X12 -> - | O11: ='Février 2026'!Y12 | P11: ='Février 2026'!Z12 -> - | Q11: ='Février 2026'!AA12 | R11: ='Février 2026'!AD12 -> 0 | S11: ='Février 2026'!AF12 -> -
A12: 10 | B12: ='Février 2026'!B13 | C12: ='Février 2026'!D13 -> - | D12: ='Février 2026'!G13 -> - | E12: ='Février 2026'!F13 -> - | F12: ='Février 2026'!I13 | G12: ='Février 2026'!K13 | H12: ='Février 2026'!L13 -> - | I12: ='Février 2026'!O13 | J12: ='Février 2026'!R13 | K12: ='Février 2026'!T13 -> 0 | L12: ='Février 2026'!V13 -> - | M12: ='Février 2026'!W13 -> - | N12: ='Février 2026'!X13 -> - | O12: ='Février 2026'!Y13 | P12: ='Février 2026'!Z13 -> - | Q12: ='Février 2026'!AA13 | R12: ='Février 2026'!AD13 -> 0 | S12: ='Février 2026'!AF13 -> -
A13: 11 | B13: ='Février 2026'!B14 | C13: ='Février 2026'!D14 -> - | D13: ='Février 2026'!G14 -> - | E13: ='Février 2026'!F14 -> - | F13: ='Février 2026'!I14 | G13: ='Février 2026'!K14 | H13: ='Février 2026'!L14 -> - | I13: ='Février 2026'!O14 | J13: ='Février 2026'!R14 | K13: ='Février 2026'!T14 -> 0 | L13: ='Février 2026'!V14 -> - | M13: ='Février 2026'!W14 -> - | N13: ='Février 2026'!X14 -> - | O13: ='Février 2026'!Y14 | P13: ='Février 2026'!Z14 -> - | Q13: ='Février 2026'!AA14 | R13: ='Février 2026'!AD14 -> 0 | S13: ='Février 2026'!AF14 -> -
A14: 12 | B14: ='Février 2026'!B15 | C14: ='Février 2026'!D15 -> - | D14: ='Février 2026'!G15 -> - | E14: ='Février 2026'!F15 -> - | F14: ='Février 2026'!I15 | G14: ='Février 2026'!K15 | H14: ='Février 2026'!L15 -> - | I14: ='Février 2026'!O15 | J14: ='Février 2026'!R15 | K14: ='Février 2026'!T15 -> 0 | L14: ='Février 2026'!V15 -> - | M14: ='Février 2026'!W15 -> - | N14: ='Février 2026'!X15 -> - | O14: ='Février 2026'!Y15 | P14: ='Février 2026'!Z15 -> - | Q14: ='Février 2026'!AA15 | R14: ='Février 2026'!AD15 -> 0 | S14: ='Février 2026'!AF15 -> -
... A30: 28 | B30: ='Février 2026'!B31 | C30: ='Février 2026'!D31 -> - | D30: ='Février 2026'!G31 -> - | E30: ='Février 2026'!F31 -> - | F30: ='Février 2026'!I31 | G30: ='Février 2026'!K31 | H30: ='Février 2026'!L31 -> - | I30: ='Février 2026'!O31 | J30: ='Février 2026'!R31 | K30: ='Février 2026'!T31 -> 0 | L30: ='Février 2026'!V31 -> - | M30: ='Février 2026'!W31 -> - | N30: ='Février 2026'!X31 -> - | O30: ='Février 2026'!Y31 | P30: ='Février 2026'!Z31 -> - | Q30: ='Février 2026'!AA31 | R30: ='Février 2026'!AD31 -> 0 | S30: ='Février 2026'!AF31 -> -
A31: 29
A32: 30
A33: 31

Sheet Récap Global
A1: 📊 RÉCAP GLOBAL — TOUS LES MOIS
A2: Mois | B2: Dépenses (€) | C2: Impressions | D2: CPM (€) | E2: Clics | F2: CTR (%) | G2: CPC (€) | H2: Vues LP | I2: Leads | J2: CPL (€) | K2: Bookings VSL | L2: Taux Book (%) | M2: Leads Non-Bookés | N2: Appels Manuels | O2: Total Appels | P2: Taux Lead→Appel (%) | Q2: Coût/Book VSL (€) | R2: Coût/Appel Manuel (€) | S2: Coût/Appel Total (€) | T2: Ventes | U2: Taux Close (%) | V2: CA Vendu (€) | W2: Cash Encaissé (€) | X2: CPA (€) | Y2: P/L (€) | Z2: ROI Vendu (%) | AA2: ROI Cash (%)
A3: Janvier 2026 (26-31) | B3: ='Janvier 2026'!B10 -> #REF! | C3: ='Janvier 2026'!C10 -> #REF! | D3: ='Janvier 2026'!D10 -> #REF! | E3: ='Janvier 2026'!E10 -> #REF! | F3: ='Janvier 2026'!F10 -> #REF! | G3: ='Janvier 2026'!G10 -> #REF! | H3: ='Janvier 2026'!I10 -> #REF! | I3: ='Janvier 2026'!K10 -> #REF! | J3: ='Janvier 2026'!L10 -> #REF! | K3: ='Janvier 2026'!O10 -> #REF! | L3: ='Janvier 2026'!P10 -> #REF! | M3: ='Janvier 2026'!Q10 -> #REF! | N3: ='Janvier 2026'!R10 -> #REF! | O3: ='Janvier 2026'!T10 -> #REF! | P3: ='Janvier 2026'!U10 -> #REF! | Q3: ='Janvier 2026'!V10 -> #REF! | R3: ='Janvier 2026'!W10 -> #REF! | S3: ='Janvier 2026'!X10 -> #REF! | T3: ='Janvier 2026'!Y10 -> #REF! | U3: ='Janvier 2026'!Z10 -> #REF! | V3: ='Janvier 2026'!AA10 -> #REF! | ... AA3: ='Janvier 2026'!AF10 -> #REF!
A4: Février 2026 | B4: ='Février 2026'!B32 -> 0 | C4: ='Février 2026'!C32 -> 0 | D4: ='Février 2026'!D32 -> - | E4: ='Février 2026'!E32 -> 0 | F4: ='Février 2026'!F32 -> - | G4: ='Février 2026'!G32 -> - | H4: ='Février 2026'!I32 -> 0 | I4: ='Février 2026'!K32 -> 0 | J4: ='Février 2026'!L32 -> - | K4: ='Février 2026'!O32 -> 0 | L4: ='Février 2026'!P32 -> - | M4: ='Février 2026'!Q32 -> 0 | N4: ='Février 2026'!R32 -> 0 | O4: ='Février 2026'!T32 -> 0 | P4: ='Février 2026'!U32 -> - | Q4: ='Février 2026'!V32 -> - | R4: ='Février 2026'!W32 -> - | S4: ='Février 2026'!X32 -> - | T4: ='Février 2026'!Y32 -> 0 | U4: ='Février 2026'!Z32 -> - | V4: ='Février 2026'!AA32 -> 0 | ... AA4: ='Février 2026'!AF32 -> -
A15: TOTAL GLOBAL | B15: =SUM(B3:B14) -> #REF! | C15: =SUM(C3:C14) -> #REF! | D15: =IF(C15=0,"-",B15/C15*1000) -> #REF! | E15: =SUM(E3:E14) -> #REF! | F15: =IF(C15=0,"-",E15/C15) -> #REF! | G15: =IF(E15=0,"-",B15/E15) -> #REF! | H15: =SUM(H3:H14) -> #REF! | I15: =SUM(I3:I14) -> #REF! | J15: =IF(I15=0,"-",B15/I15) -> #REF! | K15: =SUM(K3:K14) -> #REF! | L15: =IF(I15=0,"-",K15/I15) -> #REF! | M15: =SUM(M3:M14) -> #REF! | N15: =SUM(N3:N14) -> #REF! | O15: =SUM(O3:O14) -> #REF! | P15: =IF(I15=0,"-",O15/I15) -> #REF! | Q15: =IF(K15=0,"-",B15/K15) -> #REF! | R15: =IF(N15=0,"-",B15/N15) -> #REF! | S15: =IF(O15=0,"-",B15/O15) -> #REF! | T15: =SUM(T3:T14) -> #REF! | U15: =IF(O15=0,"-",T15/O15) -> #REF! | V15: =SUM(V3:V14) -> #REF! | W15: =SUM(W3:W14) -> #REF! | X15: =IF(T15=0,"-",B15/T15) -> #REF! | Y15: =W15-B15 -> #REF! | Z15: =IF(B15=0,"-",(V15-B15)/B15) -> #REF! | AA15: =IF(B15=0,"-",(W15-B15)/B15) -> #REF!
